MemBrainPy/Lector.py
MemBrainPy/SAT.py
MemBrainPy/SistemaP.py
MemBrainPy/__init__.py
MemBrainPy/configurador.py
MemBrainPy/funciones.py
MemBrainPy/operaciones_avanzadas.py
MemBrainPy/tests_sistemas.py
MemBrainPy/visualizadorAvanzado.py
membrainpy-0.2.1.dist-info/METADATA
membrainpy-0.2.1.dist-info/WHEEL
membrainpy-0.2.1.dist-info/top_level.txt
membrainpy-0.2.1.dist-info/RECORD
