Metadata-Version: 2.4
Name: MemBrainPy
Version: 0.2.1
Summary: Librería para realizar computación con membranas
Home-page: https://github.com/Guillemon01/MemBrainPy
Author: Guillermo Sanchis Terol
Author-email: guillesanchisterol@gmail.com
Classifier: Programming Language :: Python :: 3
Classifier: License :: OSI Approved :: MIT License
Classifier: Operating System :: OS Independent
Requires-Python: >=3.7
Requires-Dist: pandas>=1.0
Requires-Dist: matplotlib>=3.0
Dynamic: author
Dynamic: author-email
Dynamic: classifier
Dynamic: description
Dynamic: description-content-type
Dynamic: home-page
Dynamic: requires-dist
Dynamic: requires-python
Dynamic: summary
